errbot_backend_webapp/__init__.py
errbot_backend_webapp/config.py
errbot_backend_webapp/server.py
errbot_backend_webapp/webapp.plug
errbot_backend_webapp/webapp.py
errbot_backend_webapp/__pycache__/__init__.cpython-37.pyc
errbot_backend_webapp/__pycache__/config.cpython-37.pyc
errbot_backend_webapp/__pycache__/server.cpython-37.pyc
errbot_backend_webapp/__pycache__/webapp.cpython-37.pyc
errbot_backend_webapp/resources/index.html
errbot_backend_webapp/resources/static/app.css
errbot_backend_webapp/resources/static/app.js
errbot_backend_webapp-0.1.0.dist-info/LICENSE
errbot_backend_webapp-0.1.0.dist-info/METADATA
errbot_backend_webapp-0.1.0.dist-info/WHEEL
errbot_backend_webapp-0.1.0.dist-info/top_level.txt
errbot_backend_webapp-0.1.0.dist-info/RECORD
