Metadata-Version: 2.1
Name: errbot-backend-webapp
Version: 0.1.0
Summary: Webapp backend plugin for Errbot
Home-page: https://github.com/attakei/errbot-backend-webapp
Author: Kazuya Takei
Author-email: attakei@gmail.com
License: UNKNOWN
Platform: UNKNOWN
Classifier: Development Status :: 3 - Alpha
Classifier: Environment :: Plugins
Classifier: License :: OSI Approved :: GNU General Public License v3 (GPLv3)
Classifier: Programming Language :: Python :: 3.6
Classifier: Programming Language :: Python :: 3.7
Classifier: Topic :: Communications :: Chat
Requires-Dist: flask-sockets
Requires-Dist: Jinja2
